uni/lab2/verilog/contatore-modulo-4/contatore-modulo-4.v
module statouscita (output [1:0]z, input [1:0]s, input x);
	assign z[0] = (~s[0] & x) | (s[0] & ~x);
	assign z[1] = (~s[1] & s[0] & x) | (s[1] & ~s[0]) | (s[1] & s[0] & ~x);
endmodule

module registro (output [N-1:0]z, input [N-1:0]inval, input we, input clock);
	parameter N = 32;

	reg [N-1:0] S;

	initial // viene eseguito solo una volta all'inizio della simulazione
		begin
			S = 2'b00;
		end
	
	always @(posedge clock) 
		begin
			if (we==1) S = inval;
		end

	assign
		z = S;
endmodule

module coutermod4 (output [N-1:0]z, input x, input clock);
	parameter N = 2;

	wire [N-1:0] rin;
	wire [N-1:0] rout;

	registro #(N) regs(rout, rin, 1'b1, clock);
	statouscita newst(rin, rout, x);
	
	assign z = rin;
endmodule

module test();
	parameter N = 2;

	reg x;
	reg clock;
	wire [N-1:0]z;
	
	coutermod4 #(N) cnt(z, x, clock);

	initial
		begin
			$dumpfile("test.vcd");
			$dumpvars;
			//$monitor("clock: %b x: %b z: %d",clock, x , z);
			clock = 1'b0;
			x = 1'b0;
			forever #2 clock = ~clock; //simile a always, da ora in poi ogni 2t il clock cambia segno quindi il ciclo di clock dura 4t
		end
	
	initial
		begin
			#1 x = 1'b1;
			#1 x = 1'b1;
			#1 x = 1'b1;
			#1 x = 1'b1;
			#1 x = 1'b1;
			#1 x = 1'b1;
			#1 x = 1'b0;
			#1 x = 1'b1;
			#1 x = 1'b0;
			#1 x = 1'b1;
			#1 x = 1'b0;
			#1 x = 1'b1;
			#5 $finish;
		end
endmodule

uni/lab2/verilog/contatore-modulo-4/test.vcd
$date
	Wed Oct 26 13:59:56 2022
$end
$version
	Icarus Verilog
$end
$timescale
	1s
$end
$scope module test $end
$var wire 2 ! z [1:0] $end
$var reg 1 " clock $end
$var reg 1 # x $end
$scope module cnt $end
$var wire 1 " clock $end
$var wire 1 # x $end
$var wire 2 $ z [1:0] $end
$var wire 2 % rout [1:0] $end
$var wire 2 & rin [1:0] $end
$scope module newst $end
$var wire 1 # x $end
$var wire 2 ' z [1:0] $end
$var wire 2 ( s [1:0] $end
$upscope $end
$scope module regs $end
$var wire 1 " clock $end
$var wire 2 ) inval [1:0] $end
$var wire 1 * we $end
$var wire 2 + z [1:0] $end
$var reg 2 , S [1:0] $end
$upscope $end
$upscope $end
$upscope $end
$enddefinitions $end
#0
$dumpvars
b0 ,
b0 +
1*
b0 )
b0 (
b0 '
b0 &
b0 %
b0 $
0#
0"
b0 !
$end
#1
b1 !
b1 $
b1 &
b1 '
b1 )
1#
#2
b10 !
b10 $
b10 &
b10 '
b10 )
b1 %
b1 (
b1 +
b1 ,
1"
#4
0"
#6
b11 !
b11 $
b11 &
b11 '
b11 )
b10 %
b10 (
b10 +
b10 ,
1"
#7
b10 !
b10 $
b10 &
b10 '
b10 )
0#
#8
b11 !
b11 $
b11 &
b11 '
b11 )
1#
0"
#9
b10 !
b10 $
b10 &
b10 '
b10 )
0#
#10
b11 !
b11 $
b11 &
b11 '
b11 )
1#
1"
#11
b10 !
b10 $
b10 &
b10 '
b10 )
0#
#12
b11 !
b11 $
b11 &
b11 '
b11 )
1#
0"
#14
b0 !
b0 $
b0 &
b0 '
b0 )
b11 %
b11 (
b11 +
b11 ,
1"
